pyppl_runners.py
pyppl_runners-0.0.6.dist-info/entry_points.txt
pyppl_runners-0.0.6.dist-info/LICENSE
pyppl_runners-0.0.6.dist-info/WHEEL
pyppl_runners-0.0.6.dist-info/METADATA
pyppl_runners-0.0.6.dist-info/RECORD
