Metadata-Version: 2.1
Name: pyppl-runners
Version: 0.0.6
Summary: More strict check of job success for PyPPL
License: MIT
Author: pwwang
Author-email: pwwang@pwwang.com
Requires-Python: >=3.6,<4.0
Classifier: License :: OSI Approved :: MIT License
Classifier: Programming Language :: Python :: 3
Classifier: Programming Language :: Python :: 3.6
Classifier: Programming Language :: Python :: 3.7
Classifier: Programming Language :: Python :: 3.8
Requires-Dist: cmdy
Requires-Dist: diot
Requires-Dist: psutil (>=5.0.0,<6.0.0)
Requires-Dist: pyppl
